perovskite_assessment/__init__.py
perovskite_assessment/input_generation.py
perovskite_assessment/output_extraction.py
perovskite_assessment/overpotential.py
perovskite_assessment/structure_generation.py
assessPV-0.0.1.dist-info/METADATA
assessPV-0.0.1.dist-info/WHEEL
assessPV-0.0.1.dist-info/entry_points.txt
assessPV-0.0.1.dist-info/top_level.txt
assessPV-0.0.1.dist-info/RECORD
