Metadata-Version: 2.1
Name: assessPV
Version: 0.0.1
Home-page: 
Author: ['Zayah Cortright', 'Stephen Lim']
Author-email: ['zayahcortright@gmail.com', 'stephenlimzy2008@gmail.com']
Requires-Dist: ase
Requires-Dist: pandas
